<?xml version="1.0" encoding="utf-8"?>
<Positions xmlns:xsd="http://www.w3.org/2001/XMLSchema" xmlns:xsi="http://www.w3.org/2001/XMLSchema-instance">
  <Position Name="OBSERVER" Type="ASD" DefaultRange="1000">
  <Sectors>
      <Sector Name="YDL" />
	  <Sector Name="YJL" />
	  <Sector Name="YHL" />
	  <Sector Name="YCL" />
	  <Sector Name="YML" />
	  <Sector Name="YRL" />
	  <Sector Name="YOL" />
	  <Sector Name="YLL" />
	  <Sector Name="YNL" />
	  <Sector Name="YKL" />
	  <Sector Name="YSL" />
    </Sectors>
      <Maps>
      <Map Name="ALL_CTA" />
      <Map Name="ALL_SECTORS" />
      <Map Name="COAST_ALL" />
      <Map Name="ALL_ROUTES_HIGH" />
      <Map Name="ALL_POINTS_HIGH" />
      <Map Name="FIR_BDRY" />
      <Map Name="UPPER_SECTOR_FREQS" />
    </Maps>
    <Strips Mode="State" Sort="Time">
      <Window Type="State" State="Jurisdiction" Visible="true" />
      <Window Type="State" State="Announced" Visible="true" />
      <Window Type="State" State="Preactive" Visible="true" />
    </Strips>
    <ControllerInfo>
      <Line></Line>
    </ControllerInfo>
  </Position>
  
  <Position Name="DELTA" Type="ASD" DefaultRange="1000">
  <Sectors>
      <Sector Name="YDL" />
    </Sectors>
      <Maps>
      <Map Name="ALL_CTA" />
      <Map Name="ALL_SECTORS" />
      <Map Name="COAST_ALL" />
      <Map Name="ALL_ROUTES_HIGH" />
      <Map Name="ALL_POINTS_HIGH" />
      <Map Name="FIR_BDRY" />
      <Map Name="UPPER_SECTOR_FREQS" />
    </Maps>
    <Strips Mode="State" Sort="Time">
      <Window Type="State" State="Jurisdiction" Visible="true" />
      <Window Type="State" State="Announced" Visible="true" />
      <Window Type="State" State="Preactive" Visible="true" />
    </Strips>
    <ControllerInfo>
      <Line>DELTA sector</Line>
    </ControllerInfo>
  </Position>
 
    <Position Name="JEVER" Type="ASD" DefaultRange="1000">
	<Sectors>
      <Sector Name="YJL" />
    </Sectors>
	    <Maps>
      <Map Name="ALL_CTA" />
      <Map Name="ALL_SECTORS" />
      <Map Name="COAST_ALL" />
      <Map Name="ALL_ROUTES_HIGH" />
      <Map Name="ALL_POINTS_HIGH" />
      <Map Name="FIR_BDRY" />
      <Map Name="UPPER_SECTOR_FREQS" />
    </Maps>
    <Strips Mode="State" Sort="Time">
      <Window Type="State" State="Jurisdiction" Visible="true" />
      <Window Type="State" State="Announced" Visible="true" />
      <Window Type="State" State="Preactive" Visible="true" />
    </Strips>
    <ControllerInfo>
      <Line>JEVER sector</Line>
    </ControllerInfo>
  </Position>
    <Position Name="HOLSTEIN" Type="ASD" DefaultRange="1000">
  <Sectors>
      <Sector Name="YHL" />
    </Sectors>
	    <Maps>
      <Map Name="ALL_CTA" />
      <Map Name="ALL_SECTORS" />
      <Map Name="COAST_ALL" />
      <Map Name="ALL_ROUTES_HIGH" />
      <Map Name="ALL_POINTS_HIGH" />
      <Map Name="FIR_BDRY" />
      <Map Name="UPPER_SECTOR_FREQS" />
    </Maps>
    <Strips Mode="State" Sort="Time">
      <Window Type="State" State="Jurisdiction" Visible="true" />
      <Window Type="State" State="Announced" Visible="true" />
      <Window Type="State" State="Preactive" Visible="true" />
    </Strips>
    <ControllerInfo>
      <Line>HOLSTEIN sector</Line>
    </ControllerInfo>
  </Position>
    <Position Name="CELLE" Type="ASD" DefaultRange="1000">
  <Sectors>
      <Sector Name="YCL" />
    </Sectors>
	    <Maps>
      <Map Name="ALL_CTA" />
      <Map Name="ALL_SECTORS" />
      <Map Name="COAST_ALL" />
      <Map Name="ALL_ROUTES_HIGH" />
      <Map Name="ALL_POINTS_HIGH" />
      <Map Name="FIR_BDRY" />
      <Map Name="UPPER_SECTOR_FREQS" />
    </Maps>
    <Strips Mode="State" Sort="Time">
      <Window Type="State" State="Jurisdiction" Visible="true" />
      <Window Type="State" State="Announced" Visible="true" />
      <Window Type="State" State="Preactive" Visible="true" />
    </Strips>
    <ControllerInfo>
      <Line>CELLE sector</Line>
    </ControllerInfo>
  </Position>  

    <Position Name="SOLLING" Type="ASD" DefaultRange="1000">
  <Sectors>
      <Sector Name="YSL" />
    </Sectors>
	    <Maps>
      <Map Name="ALL_CTA" />
      <Map Name="ALL_SECTORS" />
      <Map Name="COAST_ALL" />
      <Map Name="ALL_ROUTES_HIGH" />
      <Map Name="ALL_POINTS_HIGH" />
      <Map Name="FIR_BDRY" />
      <Map Name="UPPER_SECTOR_FREQS" />
    </Maps>
    <Strips Mode="State" Sort="Time">
      <Window Type="State" State="Jurisdiction" Visible="true" />
      <Window Type="State" State="Announced" Visible="true" />
      <Window Type="State" State="Preactive" Visible="true" />
    </Strips>
    <ControllerInfo>
      <Line>SOLLING sector</Line>
    </ControllerInfo>
  </Position>

    <Position Name="MUENSTER" Type="ASD" DefaultRange="1000">
  <Sectors>
      <Sector Name="YML" />
    </Sectors>
	    <Maps>
      <Map Name="ALL_CTA" />
      <Map Name="ALL_SECTORS" />
      <Map Name="COAST_ALL" />
      <Map Name="ALL_ROUTES_HIGH" />
      <Map Name="ALL_POINTS_HIGH" />
      <Map Name="FIR_BDRY" />
      <Map Name="UPPER_SECTOR_FREQS" />
    </Maps>
    <Strips Mode="State" Sort="Time">
      <Window Type="State" State="Jurisdiction" Visible="true" />
      <Window Type="State" State="Announced" Visible="true" />
      <Window Type="State" State="Preactive" Visible="true" />
    </Strips>
    <ControllerInfo>
      <Line>MUENSTER sector</Line>
    </ControllerInfo>
  </Position>

    <Position Name="RUHR" Type="ASD" DefaultRange="1000">
  <Sectors>
      <Sector Name="YRL" />
    </Sectors>
	    <Maps>
      <Map Name="ALL_CTA" />
      <Map Name="ALL_SECTORS" />
      <Map Name="COAST_ALL" />
      <Map Name="ALL_ROUTES_HIGH" />
      <Map Name="ALL_POINTS_HIGH" />
      <Map Name="FIR_BDRY" />
      <Map Name="UPPER_SECTOR_FREQS" />
    </Maps>
    <Strips Mode="State" Sort="Time">
      <Window Type="State" State="Jurisdiction" Visible="true" />
      <Window Type="State" State="Announced" Visible="true" />
      <Window Type="State" State="Preactive" Visible="true" />
    </Strips>
    <ControllerInfo>
      <Line>RUHR sector</Line>
    </ControllerInfo>
  </Position>

    <Position Name="OLNO" Type="ASD" DefaultRange="1000">
  <Sectors>
      <Sector Name="YOL" />
    </Sectors>
	 <Maps>
      <Map Name="ALL_CTA" />
      <Map Name="ALL_SECTORS" />
      <Map Name="COAST_ALL" />
      <Map Name="ALL_ROUTES_HIGH" />
      <Map Name="ALL_POINTS_HIGH" />
      <Map Name="FIR_BDRY" />
      <Map Name="UPPER_SECTOR_FREQS" />
    </Maps>
    <Strips Mode="State" Sort="Time">
      <Window Type="State" State="Jurisdiction" Visible="true" />
      <Window Type="State" State="Announced" Visible="true" />
      <Window Type="State" State="Preactive" Visible="true" />
    </Strips>
    <ControllerInfo>
      <Line>OLNO sector</Line>
    </ControllerInfo>
  </Position>

    <Position Name="LUX" Type="ASD" DefaultRange="1000">
  <Sectors>
      <Sector Name="YLL" />
    </Sectors>
	    <Maps>
      <Map Name="ALL_CTA" />
      <Map Name="ALL_SECTORS" />
      <Map Name="COAST_ALL" />
      <Map Name="ALL_ROUTES_HIGH" />
      <Map Name="ALL_POINTS_HIGH" />
      <Map Name="FIR_BDRY" />
      <Map Name="UPPER_SECTOR_FREQS" />
    </Maps>
    <Strips Mode="State" Sort="Time">
      <Window Type="State" State="Jurisdiction" Visible="true" />
      <Window Type="State" State="Announced" Visible="true" />
      <Window Type="State" State="Preactive" Visible="true" />
    </Strips>
    <ControllerInfo>
      <Line>LUX sector</Line>
    </ControllerInfo>
  </Position>

    <Position Name="NICKY" Type="ASD" DefaultRange="1000">
  <Sectors>
      <Sector Name="YNL" />
    </Sectors>
	    <Maps>
      <Map Name="ALL_CTA" />
      <Map Name="ALL_SECTORS" />
      <Map Name="COAST_ALL" />
      <Map Name="ALL_ROUTES_HIGH" />
      <Map Name="ALL_POINTS_HIGH" />
      <Map Name="FIR_BDRY" />
      <Map Name="UPPER_SECTOR_FREQS" />
    </Maps>
    <Strips Mode="State" Sort="Time">
      <Window Type="State" State="Jurisdiction" Visible="true" />
      <Window Type="State" State="Announced" Visible="true" />
      <Window Type="State" State="Preactive" Visible="true" />
    </Strips>
    <ControllerInfo>
      <Line>NICKY sector</Line>
    </ControllerInfo>
  </Position>

    <Position Name="KOKSY" Type="ASD" DefaultRange="1000">
  <Sectors>
      <Sector Name="YKL" />
    </Sectors>
	    <Maps>
      <Map Name="ALL_CTA" />
      <Map Name="ALL_SECTORS" />
      <Map Name="COAST_ALL" />
      <Map Name="ALL_ROUTES_HIGH" />
      <Map Name="ALL_POINTS_HIGH" />
      <Map Name="FIR_BDRY" />
      <Map Name="UPPER_SECTOR_FREQS" />
    </Maps>
    <Strips Mode="State" Sort="Time">
      <Window Type="State" State="Jurisdiction" Visible="true" />
      <Window Type="State" State="Announced" Visible="true" />
      <Window Type="State" State="Preactive" Visible="true" />
    </Strips>
    <ControllerInfo>
      <Line>KOKSY sector</Line>
    </ControllerInfo>
  </Position>
</Positions>